.drone.yml
.gitignore
.gitmodules
.travis.yml
AUTHORS
CHANGES.rst
LICENSE
MANIFEST.in
README.rst
appveyor.yml
setup.cfg
setup.py
.circleci/config.yml
.gh-pages-skeleton/.nojekyll
conda-recipe/meta.yaml
examples/Makefile
examples/adapted_grid.ipynb
examples/adapted_grid_peak.ipynb
examples/adapted_grid_tolerance.ipynb
examples/demo.cpp
examples/discontinuity.ipynb
examples/err.py
examples/sine.py
examples/tests/test_examples.py
finitediff/__init__.py
finitediff/_config.py
finitediff/_finitediff_c.c
finitediff/_finitediff_c.pyx
finitediff/_release.py
finitediff/util.py
finitediff.egg-info/PKG-INFO
finitediff.egg-info/SOURCES.txt
finitediff.egg-info/dependency_links.txt
finitediff.egg-info/requires.txt
finitediff.egg-info/top_level.txt
finitediff/external/newton_interval/.drone.yml
finitediff/external/newton_interval/.git
finitediff/external/newton_interval/.gitignore
finitediff/external/newton_interval/.travis.yml
finitediff/external/newton_interval/AUTHORS
finitediff/external/newton_interval/LICENSE
finitediff/external/newton_interval/README.rst
finitediff/external/newton_interval/include/newton_interval.h
finitediff/external/newton_interval/include/newton_interval.pxd
finitediff/external/newton_interval/src/newton_interval.c
finitediff/external/newton_interval/tests/Makefile
finitediff/external/newton_interval/tests/test_check_nan.c
finitediff/external/newton_interval/tests/test_check_strict_monotonicity.c
finitediff/external/newton_interval/tests/test_newton_interval.c
finitediff/external/newton_interval/tests/unittest.c
finitediff/external/newton_interval/tests/unittest.h
finitediff/grid/__init__.py
finitediff/grid/make.py
finitediff/grid/plotting.py
finitediff/grid/rebalance.py
finitediff/grid/refine.py
finitediff/grid/util.py
finitediff/grid/tests/__init__.py
finitediff/grid/tests/_common.py
finitediff/grid/tests/test_make.py
finitediff/grid/tests/test_rebalance.py
finitediff/grid/tests/test_refine.py
finitediff/grid/tests/test_util.py
finitediff/include/c_finitediff_fort.h
finitediff/include/c_finitediff_fort.pxd
finitediff/include/finitediff_c.h
finitediff/include/finitediff_c.pxd
finitediff/include/finitediff_templated.hpp
