Metadata-Version: 2.1
Name: finitediff
Version: 0.6.4
Summary: Finite difference weights for any derivative order on arbitrarily spaced grids.
Home-page: https://github.com/bjodah/finitediff
Author: Björn Dahlgren
Author-email: bjodah@gmail.com
License: BSD
Keywords: finite-difference,taylor series,extrapolation,interpolation
Platform: UNKNOWN
Classifier: Development Status :: 4 - Beta
Classifier: License :: OSI Approved :: BSD License
Classifier: Operating System :: OS Independent
Classifier: Topic :: Scientific/Engineering
Classifier: Topic :: Scientific/Engineering :: Mathematics
Provides-Extra: all
